Metadata-Version: 1.0
Name: s3pd
Version: 1.2.0
Summary: S3 parallel downloader
Home-page: UNKNOWN
Author: Aurelien Vallee
Author-email: vallee.aurelien@gmail.com
License: UNKNOWN
Platform: UNKNOWN
